eargait/__init__.py
eargait/base/__init__.py
eargait/base/base_eargait.py
eargait/eargait.py
eargait/event_detection/__init__.py
eargait/event_detection/base_event_detection.py
eargait/event_detection/diao_adapted_event_detection.py
eargait/event_detection/diao_event_detection.py
eargait/event_detection/jarchi_event_detection.py
eargait/event_detection/mixed_event_detection.py
eargait/gait_sequence_detection/__init__.py
eargait/gait_sequence_detection/configuration.py
eargait/gait_sequence_detection/conv_gru.py
eargait/gait_sequence_detection/gait_sequence_detector.py
eargait/gait_sequence_detection/har_predictor.py
eargait/gait_sequence_detection/pretrained_models/200hz_grav_align/default87/version_0/checkpoints/epoch=25-step=24959.ckpt
eargait/gait_sequence_detection/pretrained_models/200hz_grav_align/default87/version_0/hparams.yaml
eargait/gait_sequence_detection/pretrained_models/200hz_grav_align_off/default/version_0/checkpoints/epoch=59-step=115139.ckpt
eargait/gait_sequence_detection/pretrained_models/200hz_grav_align_off/default/version_0/hparams.yaml
eargait/gait_sequence_detection/pretrained_models/200hz_gravity_aligned_scaler.save
eargait/gait_sequence_detection/pretrained_models/50hz_grav_align/version_0/checkpoints/epoch=36-step=69818.ckpt
eargait/gait_sequence_detection/pretrained_models/50hz_grav_align/version_0/hparams.yaml
eargait/gait_sequence_detection/pretrained_models/50hz_gravity_aligned_scaler.save
eargait/preprocessing/__init__.py
eargait/preprocessing/load_data_helpers.py
eargait/preprocessing/rotations.py
eargait/spatial_params/__init__.py
eargait/spatial_params/data_vector_loader.py
eargait/spatial_params/feature_extractor.py
eargait/spatial_params/spatial_params_base.py
eargait/spatial_params/spatial_params_cnn.py
eargait/spatial_params/spatial_params_example_class.py
eargait/spatial_params/spatial_params_inverted_pendulum.py
eargait/spatial_params/spatial_params_rf.py
eargait-3.2.0.dist-info/LICENSE
eargait-3.2.0.dist-info/METADATA
eargait-3.2.0.dist-info/WHEEL
eargait-3.2.0.dist-info/RECORD
