Metadata-Version: 2.3
Name: eargait
Version: 3.2.0
Summary: *Eargait* provides a set of algorithms and functions to process IMU data recorded with ear-worn IMU sensors and to estimate characteristic gait parameters. 
Author: Ann-Kristin Seifer
Author-email: ann-kristin.seifer@fau.de
Requires-Python: >=3.10,<3.12
Classifier: Programming Language :: Python :: 3
Classifier: Programming Language :: Python :: 3.10
Classifier: Programming Language :: Python :: 3.11
Requires-Dist: debugpy (==1.6.4)
Requires-Dist: fau-colors (>=1.0.1,<2.0.0)
Requires-Dist: imbalanced-learn (==0.8.1)
Requires-Dist: intervaltree (==3.1.0)
Requires-Dist: joblib (>=1.2.0)
Requires-Dist: matplotlib (>=3.5.2,<3.9.0)
Requires-Dist: nilspodlib (>=3.2.2,<4.0.0)
Requires-Dist: numba (>=0.55)
Requires-Dist: numba (>=0.55.2) ; sys_platform == "darwin" and platform_machine == "arm64"
Requires-Dist: numpy (>=1.20,<2.0.0)
Requires-Dist: pandas (>=1.5.2)
Requires-Dist: pytorch-lightning (>=2.0.0,<3.0.0)
Requires-Dist: pyts (>=0.11.0,<0.12.0)
Requires-Dist: scikit-learn (==1.2.0)
Requires-Dist: scipy (>=1.14,<2.0)
Requires-Dist: signialib (>=2.8.0,<3.0.0)
Requires-Dist: tensorflow (>=2.10.0,<2.17.0)
Requires-Dist: tensorflow-io-gcs-filesystem (==0.30.0) ; sys_platform == "win32"
Requires-Dist: tensorflow-io-gcs-filesystem (>=0.34.0,<0.35.0) ; sys_platform == "darwin"
Requires-Dist: tensorflow-io-gcs-filesystem (>=0.34.0,<0.35.0) ; sys_platform == "linux"
Requires-Dist: torch (>=2.0.0,!=2.0.1,!=2.1.0,<2.3.0)
Requires-Dist: tpcp (>=0.30.3,<1.0.0)
Project-URL: Homepage, https://github.com/mad-lab-fau/eargait
Project-URL: Repository, https://github.com/mad-lab-fau/eargait
